{"matches": [], "playerInfo": {"tier": "MASTER", "rank": "I", "leaguePoints": 0, "profileIconId": 3148, "name": "ajswagatron", "region": "na1", "localRank": [16991, 0.01809518636732025], "globalRank": [87403, 0.016875782095178076]}, "rankHistory": [[1645130825029, "DIAMOND II", 16, 5], [1645132629323, "DIAMOND II", 0, 6], [1645136231011, "DIAMOND II", 59, 7], [1645138029720, "DIAMOND I", 16, 8], [1645141630931, "DIAMOND I", 46, 9], [1645390025025, "MASTER I", 2, 10], [1646293626824, "MASTER I", 0, 10]], "seasonStats": {"games": 14, "avgPlace": 3.2857142857142856, "top4": 9, "win": 5, "topCarry": "TFT6_KhaZix", "lastMatchId": "NA1_4316895917"}, "queueSeasonStats": {"1090": {"games": 1, "avgPlace": 1, "top4": 1, "win": 1, "topCarry": "TFT6_Lucian", "lastMatchId": "NA1_4316895917"}, "1100": {"games": 10, "avgPlace": 3.1, "top4": 7, "win": 4, "topCarry": "TFT6_KhaZix", "lastMatchId": "NA1_4316895917"}, "1130": {"games": 0, "avgPlace": 0, "top4": 0, "win": 0, "topCarry": "TFT6_Veigar", "lastMatchId": "NA1_4316895917"}, "1150": {"games": 3, "avgPlace": 4.666666666666667, "top4": 1, "win": 0, "topCarry": "TFT6_Talon", "lastMatchId": "NA1_4316895917"}}}