{"matches": [], "playerInfo": {"tier": "MASTER", "rank": "I", "leaguePoints": 0, "profileIconId": 29, "name": "Ca1vinC", "region": "na1", "localRank": [7757, 0.008250714505281542], "globalRank": [42176, 0.008138344131780353]}, "rankHistory": [[1648021918879, "GOLD IV", 51, 5], [1648102911009, "GOLD III", 18, 6], [1648104628548, "GOLD II", 20, 7], [1649852522061, "GOLD I", 13, 8], [1650125995542, "PLATINUM IV", 68, 10], [1650351717957, "PLATINUM III", 60, 11], [1650354598304, "PLATINUM II", 38, 12], [1650392343482, "PLATINUM I", 6, 13], [1650395912708, "PLATINUM I", 0, 14], [1650433688786, "PLATINUM I", 41, 15], [1650439105433, "PLATINUM I", 74, 16], [1650443403592, "DIAMOND IV", 37, 17], [1650448951642, "DIAMOND IV", 58, 18], [1650452091724, "DIAMOND III", 26, 19], [1650529503561, "DIAMOND III", 68, 20], [1650531780811, "DIAMOND III", 40, 21], [1650611854011, "DIAMOND III", 22, 22], [1651182909222, "DIAMOND III", 46, 23], [1651185211465, "DIAMOND III", 18, 24], [1651334134092, "DIAMOND III", 94, 25], [1651337274206, "DIAMOND II", 4, 26], [1651339530994, "DIAMOND II", 65, 27], [1651342666877, "DIAMOND I", 10, 28], [1651345421901, "DIAMOND I", 51, 29], [1651348040773, "DIAMOND I", 92, 30], [1651350788081, "MASTER I", 50, 31], [1651526691456, "MASTER I", 37, 32], [1652338514614, "MASTER I", 0, 32]], "seasonStats": {"games": 32, "avgPlace": 2.3125, "top4": 27, "win": 15, "topCarry": "TFT6_Jhin", "lastMatchId": "NA1_4295576418"}, "queueSeasonStats": {"1090": {"games": 0, "avgPlace": 0, "top4": 0, "win": 0, "topCarry": "TFT6_Veigar", "lastMatchId": "NA1_4295576418"}, "1100": {"games": 32, "avgPlace": 2.3125, "top4": 27, "win": 15, "topCarry": "TFT6_Jhin", "lastMatchId": "NA1_4295576418"}, "1130": {"games": 0, "avgPlace": 0, "top4": 0, "win": 0, "topCarry": "TFT6_Veigar", "lastMatchId": "NA1_4295576418"}, "1150": {"games": 0, "avgPlace": 0, "top4": 0, "win": 0, "topCarry": "TFT6_Veigar", "lastMatchId": "NA1_4295576418"}}}