{"matches": [], "playerInfo": {"tier": "MASTER", "rank": "I", "leaguePoints": 0, "profileIconId": 5316, "name": "Chef John", "region": "na1", "localRank": [9680, 0.010318157398801047], "globalRank": [52513, 0.010147884747794733]}, "rankHistory": [[1647579852344, "DIAMOND II", 52, 5], [1647746991309, "DIAMOND II", 42, 6], [1647749842134, "DIAMOND II", 74, 7], [1647751992242, "DIAMOND I", 24, 8], [1647755985658, "DIAMOND I", 45, 9], [1647757767906, "DIAMOND I", 35, 10], [1647759585506, "DIAMOND I", 25, 11], [1647761688791, "DIAMOND I", 0, 12], [1647764237053, "DIAMOND II", 75, 13], [1649653340364, "DIAMOND I", 9, 14], [1649971935080, "DIAMOND I", 0, 15], [1649973716605, "DIAMOND II", 75, 16], [1649976447420, "DIAMOND I", 28, 17], [1649978275836, "DIAMOND I", 38, 18], [1649980453934, "DIAMOND I", 59, 19], [1649982259463, "DIAMOND I", 28, 20], [1649984073837, "DIAMOND I", 9, 21], [1649985868666, "DIAMOND I", 0, 22], [1649987679318, "DIAMOND I", 34, 23], [1649990332781, "DIAMOND I", 78, 24], [1649992135675, "DIAMOND I", 47, 25], [1649993921651, "DIAMOND I", 57, 26], [1649996254637, "DIAMOND I", 75, 27], [1649998914373, "MASTER I", 21, 28], [1650242327151, "MASTER I", 31, 29], [1650244630989, "MASTER I", 10, 30], [1650246856013, "MASTER I", 0, 31], [1650695556783, "MASTER I", 44, 32], [1651215284822, "MASTER I", 0, 32]], "seasonStats": {"games": 117, "avgPlace": 3.9914529914529915, "top4": 68, "win": 18, "topCarry": "TFT6_Jhin", "lastMatchId": "NA1_4285746395"}, "queueSeasonStats": {"1090": {"games": 4, "avgPlace": 5.25, "top4": 2, "win": 0, "topCarry": "TFT6_Jinx", "lastMatchId": "NA1_4285746395"}, "1100": {"games": 32, "avgPlace": 3.84375, "top4": 19, "win": 6, "topCarry": "TFT6_Jhin", "lastMatchId": "NA1_4285746395"}, "1130": {"games": 48, "avgPlace": 3.8125, "top4": 29, "win": 12, "topCarry": "TFT6_Jhin", "lastMatchId": "NA1_4285746395"}, "1150": {"games": 33, "avgPlace": 4.242424242424242, "top4": 18, "win": 0, "topCarry": "TFT6_Jhin", "lastMatchId": "NA1_4285746395"}}}