{"matches": [], "playerInfo": {"tier": "MASTER", "rank": "I", "leaguePoints": 0, "profileIconId": 29, "name": "lil yung chug", "region": "na1", "localRank": [18847, 0.020050063989565926], "globalRank": [96011, 0.0185280423564275]}, "rankHistory": [[1649315947530, "PLATINUM I", 69, 5], [1649317719150, "PLATINUM I", 44, 6], [1649395919251, "DIAMOND IV", 3, 7], [1649398647562, "DIAMOND IV", 62, 8], [1649491316830, "DIAMOND IV", 52, 9], [1649493474276, "DIAMOND IV", 42, 10], [1649543488096, "DIAMOND IV", 32, 11], [1649545322797, "DIAMOND IV", 0, 12], [1649548901489, "DIAMOND IV", 0, 13], [1649551095755, "DIAMOND IV", 54, 14], [1649563690869, "DIAMOND IV", 64, 15], [1649569079728, "DIAMOND III", 4, 16], [1649571455610, "DIAMOND III", 43, 17], [1649573668241, "DIAMOND III", 53, 18], [1649650654706, "DIAMOND III", 75, 19], [1649652447522, "DIAMOND III", 55, 20], [1649654653305, "DIAMOND III", 91, 21], [1649744671468, "DIAMOND III", 73, 22], [1649747306767, "DIAMOND III", 63, 23], [1649749663938, "DIAMOND III", 87, 24], [1649919711976, "DIAMOND III", 97, 25], [1649921559051, "DIAMOND III", 61, 26], [1649923706674, "DIAMOND III", 71, 27], [1649983111994, "DIAMOND III", 96, 28], [1649993551885, "DIAMOND II", 17, 29], [1649999844863, "DIAMOND II", 0, 30], [1650002089806, "DIAMOND II", 24, 31], [1650067728065, "DIAMOND II", 14, 32], [1650093884663, "DIAMOND II", 60, 33], [1650096134028, "DIAMOND II", 70, 34], [1650142452707, "DIAMOND I", 3, 35], [1650144746148, "DIAMOND I", 13, 36], [1650146922209, "DIAMOND I", 61, 37], [1650164927508, "DIAMOND I", 41, 38], [1650167239827, "DIAMOND I", 31, 39], [1650169487273, "DIAMOND I", 66, 40], [1650172650188, "DIAMOND I", 56, 41], [1650174899746, "DIAMOND I", 89, 42], [1650231780709, "DIAMOND I", 99, 43], [1650233943511, "MASTER I", 31, 44], [1651128883013, "MASTER I", 0, 44]], "seasonStats": {"games": 44, "avgPlace": 4.136363636363637, "top4": 25, "win": 5, "topCarry": "TFT6_Sivir", "lastMatchId": "NA1_4280260639"}, "queueSeasonStats": {"1090": {"games": 0, "avgPlace": 0, "top4": 0, "win": 0, "topCarry": "TFT6_Veigar", "lastMatchId": "NA1_4280260639"}, "1100": {"games": 44, "avgPlace": 4.136363636363637, "top4": 25, "win": 5, "topCarry": "TFT6_Sivir", "lastMatchId": "NA1_4280260639"}, "1130": {"games": 0, "avgPlace": 0, "top4": 0, "win": 0, "topCarry": "TFT6_Veigar", "lastMatchId": "NA1_4280260639"}, "1150": {"games": 0, "avgPlace": 0, "top4": 0, "win": 0, "topCarry": "TFT6_Veigar", "lastMatchId": "NA1_4280260639"}}}