{"matches": [], "playerInfo": {"tier": "MASTER", "rank": "I", "leaguePoints": 0, "profileIconId": 3180, "name": "n\u00e8ne", "region": "na1", "localRank": [11481, 0.012210075838385858], "globalRank": [61460, 0.011858608189926048]}, "rankHistory": [[1645040923041, "DIAMOND III", 25, 5], [1645607827675, "DIAMOND III", 78, 6], [1645611904768, "DIAMOND II", 18, 7], [1645613239605, "DIAMOND II", 0, 8], [1645618625735, "DIAMOND II", 10, 9], [1645620439726, "DIAMOND II", 0, 10], [1645622715612, "DIAMOND II", 21, 11], [1645625835021, "DIAMOND II", 0, 12], [1645627838614, "DIAMOND II", 37, 13], [1645629634724, "DIAMOND II", 7, 14], [1648343132322, "DIAMOND II", 0, 15], [1648345664529, "DIAMOND II", 34, 16], [1648347828962, "DIAMOND II", 52, 17], [1648350335706, "DIAMOND II", 96, 18], [1648380934832, "DIAMOND II", 73, 19], [1648383437214, "DIAMOND I", 2, 20], [1648385256389, "DIAMOND I", 0, 21], [1648407611730, "DIAMOND II", 75, 22], [1648409412547, "DIAMOND II", 54, 23], [1648412240043, "DIAMOND II", 84, 24], [1648414030437, "DIAMOND I", 28, 25], [1648416206284, "DIAMOND I", 48, 26], [1648418429413, "DIAMOND I", 58, 27], [1648421230577, "DIAMOND I", 68, 28], [1648422038036, "DIAMOND I", 10, 29], [1648424852803, "DIAMOND I", 0, 30], [1648425970063, "DIAMOND I", 19, 31], [1648428833496, "DIAMOND I", 50, 32], [1648431028158, "DIAMOND I", 81, 33], [1648433155657, "MASTER I", 23, 34], [1649314423717, "MASTER I", 0, 34]], "seasonStats": {"games": 45, "avgPlace": 4, "top4": 28, "win": 5, "topCarry": "TFT6_Irelia", "lastMatchId": "NA1_4259312060"}, "queueSeasonStats": {"1090": {"games": 1, "avgPlace": 1, "top4": 1, "win": 1, "topCarry": "TFT6_Warwick", "lastMatchId": "NA1_4259312060"}, "1100": {"games": 34, "avgPlace": 4.235294117647059, "top4": 20, "win": 4, "topCarry": "TFT6_Irelia", "lastMatchId": "NA1_4259312060"}, "1130": {"games": 0, "avgPlace": 0, "top4": 0, "win": 0, "topCarry": "TFT6_Veigar", "lastMatchId": "NA1_4259312060"}, "1150": {"games": 10, "avgPlace": 3.5, "top4": 7, "win": 0, "topCarry": "TFT6_Irelia", "lastMatchId": "NA1_4259312060"}}}