{"matches": [], "playerInfo": {"tier": "MASTER", "rank": "I", "leaguePoints": 0, "profileIconId": 5278, "name": "TheChosenZygote", "region": "na1", "localRank": [7787, 0.008299246065664973], "globalRank": [43373, 0.00838056939875844]}, "rankHistory": [[1652064115492, "DIAMOND III", 20, 5], [1652240859264, "DIAMOND III", 58, 6], [1652243694344, "DIAMOND III", 78, 7], [1652316956552, "DIAMOND II", 1, 8], [1652331348441, "DIAMOND II", 11, 9], [1652465566329, "DIAMOND II", 0, 10], [1652636883904, "DIAMOND III", 75, 11], [1652658978998, "DIAMOND III", 85, 12], [1652679265350, "DIAMOND II", 19, 13], [1652843100649, "DIAMOND II", 29, 14], [1652845400836, "DIAMOND II", 82, 15], [1652938476419, "DIAMOND I", 20, 16], [1652940812167, "DIAMOND I", 2, 17], [1652942093438, "DIAMOND I", 0, 18], [1653059098874, "DIAMOND II", 75, 19], [1653545651173, "DIAMOND I", 12, 20], [1653547440823, "DIAMOND I", 22, 21], [1653612439954, "DIAMOND I", 69, 22], [1653686782837, "DIAMOND I", 59, 23], [1653697076863, "DIAMOND I", 79, 24], [1653699919584, "MASTER I", 23, 25], [1654020326821, "MASTER I", 0, 26]], "seasonStats": {"games": 60, "avgPlace": 3.6, "top4": 41, "win": 16, "topCarry": "TFT6_Draven", "lastMatchId": "NA1_4326272779"}, "queueSeasonStats": {"1090": {"games": 0, "avgPlace": 0, "top4": 0, "win": 0, "topCarry": "TFT6_Veigar", "lastMatchId": "NA1_4326272779"}, "1100": {"games": 26, "avgPlace": 4.115384615384615, "top4": 16, "win": 4, "topCarry": "TFT6_Jhin", "lastMatchId": "NA1_4326272779"}, "1130": {"games": 0, "avgPlace": 0, "top4": 0, "win": 0, "topCarry": "TFT6_Veigar", "lastMatchId": "NA1_4326272779"}, "1150": {"games": 34, "avgPlace": 3.2058823529411766, "top4": 25, "win": 12, "topCarry": "TFT6_Draven", "lastMatchId": "NA1_4326272779"}}}