{"matches": [], "playerInfo": {"tier": "MASTER", "rank": "I", "leaguePoints": 0, "profileIconId": 5227, "name": "Trafalgarx08", "region": "na1", "localRank": [7775, 0.00828345503708644], "globalRank": [43042, 0.008312882031509072]}, "rankHistory": [[1645066025494, "DIAMOND II", 67, 5], [1645080426947, "DIAMOND II", 57, 6], [1645082225343, "DIAMOND II", 93, 7], [1645084028225, "DIAMOND II", 47, 8], [1645085828220, "DIAMOND II", 57, 9], [1645087625927, "DIAMOND II", 84, 10], [1645089428424, "DIAMOND II", 39, 11], [1645094826467, "DIAMOND II", 60, 12], [1645098424864, "DIAMOND II", 97, 13], [1645100228994, "DIAMOND I", 32, 14], [1645105627962, "DIAMOND I", 83, 15], [1645109224496, "MASTER I", 31, 16], [1646034425095, "MASTER I", 0, 16]], "seasonStats": {"games": 27, "avgPlace": 3.5185185185185186, "top4": 20, "win": 6, "topCarry": "TFT6_Irelia", "lastMatchId": "NA1_4221861724"}, "queueSeasonStats": {"1090": {"games": 11, "avgPlace": 4, "top4": 7, "win": 2, "topCarry": "TFT6_Irelia", "lastMatchId": "NA1_4221861724"}, "1100": {"games": 16, "avgPlace": 3.1875, "top4": 13, "win": 4, "topCarry": "TFT6_Irelia", "lastMatchId": "NA1_4221861724"}, "1130": {"games": 0, "avgPlace": 0, "top4": 0, "win": 0, "topCarry": "TFT6_Veigar", "lastMatchId": "NA1_4221861724"}, "1150": {"games": 0, "avgPlace": 0, "top4": 0, "win": 0, "topCarry": "TFT6_Veigar", "lastMatchId": "NA1_4221861724"}}}